ttycolor/__init__.py
ttycolor/color.py
tty_color-1.0.0.dist-info/METADATA
tty_color-1.0.0.dist-info/WHEEL
tty_color-1.0.0.dist-info/top_level.txt
tty_color-1.0.0.dist-info/RECORD
