Metadata-Version: 2.1
Name: tty-color
Version: 1.0.0
Summary: Package for manage colors in console
Home-page: https://github.com/Christophedlr/tty-color
Author: Christophe Daloz - De Los Rios
Author-email: christophedlr@gmail.com
License: MIT
Keywords: console,tty,color
Platform: UNKNOWN
Classifier: Programming Language :: Python :: 3
Classifier: License :: OSI Approved :: MIT License
Classifier: Operating System :: OS Independent
Classifier: Environment :: Console
Requires-Python: >=3.8
